README.md
setup.cfg
setup.py
channelengine_channel_api_client/__init__.py
channelengine_channel_api_client/api_client.py
channelengine_channel_api_client/configuration.py
channelengine_channel_api_client/exceptions.py
channelengine_channel_api_client/model_utils.py
channelengine_channel_api_client/rest.py
channelengine_channel_api_client.egg-info/PKG-INFO
channelengine_channel_api_client.egg-info/SOURCES.txt
channelengine_channel_api_client.egg-info/dependency_links.txt
channelengine_channel_api_client.egg-info/requires.txt
channelengine_channel_api_client.egg-info/top_level.txt
channelengine_channel_api_client/api/__init__.py
channelengine_channel_api_client/api/cancellation_api.py
channelengine_channel_api_client/api/order_api.py
channelengine_channel_api_client/api/product_api.py
channelengine_channel_api_client/api/return_api.py
channelengine_channel_api_client/api/shipment_api.py
channelengine_channel_api_client/apis/__init__.py
channelengine_channel_api_client/model/__init__.py
channelengine_channel_api_client/model/api_response.py
channelengine_channel_api_client/model/channel_address_request.py
channelengine_channel_api_client/model/channel_cancellation_line_response.py
channelengine_channel_api_client/model/channel_cancellation_response.py
channelengine_channel_api_client/model/channel_offer_response.py
channelengine_channel_api_client/model/channel_order_line_request.py
channelengine_channel_api_client/model/channel_order_line_response.py
channelengine_channel_api_client/model/channel_order_request.py
channelengine_channel_api_client/model/channel_processed_changes_request.py
channelengine_channel_api_client/model/channel_product_changes_response.py
channelengine_channel_api_client/model/channel_product_extra_data_item_response.py
channelengine_channel_api_client/model/channel_product_references_request.py
channelengine_channel_api_client/model/channel_product_response.py
channelengine_channel_api_client/model/channel_return_line_request.py
channelengine_channel_api_client/model/channel_return_line_response.py
channelengine_channel_api_client/model/channel_return_request.py
channelengine_channel_api_client/model/channel_return_response.py
channelengine_channel_api_client/model/channel_return_status.py
