Metadata-Version: 1.2
Name: channelengine-channel-api-client
Version: 2.12.0
Summary: ChannelEngine Channel API
Home-page: https://github.com/channelengine/channel-api-client-python
Author: OpenAPI Generator community
Author-email: team@openapitools.org
License: UNKNOWN
Keywords: OpenAPI,OpenAPI-Generator,ChannelEngine Channel API
Platform: UNKNOWN
Requires-Python: >=3.6
